genagent/__init__.py
genagent/agent_utils.py
genagent/async_utils.py
genagent/experiment_utils.py
genagent/llm_utils.py
genagent-0.4.1.dist-info/licenses/LICENSE
genagent-0.4.1.dist-info/METADATA
genagent-0.4.1.dist-info/WHEEL
genagent-0.4.1.dist-info/top_level.txt
genagent-0.4.1.dist-info/RECORD
