Metadata-Version: 2.4
Name: genagent
Version: 0.4.1
Summary: Python utilities for generative agent tasks, including LLM interactions and agent memory.
Author-email: Carolyn Zou <cqz@cs.stanford.edu>
Classifier: Programming Language :: Python :: 3
Classifier: Operating System :: OS Independent
Requires-Python: >=3.8
License-File: LICENSE
Requires-Dist: openai>=1.0.0
Requires-Dist: anthropic>=0.20.0
Requires-Dist: cerebras-cloud-sdk>=1.0.0
Requires-Dist: pydantic>=2.0.0
Requires-Dist: numpy>=1.20.0
Requires-Dist: python-dotenv>=0.20.0
Requires-Dist: tqdm>=4.60.0
Requires-Dist: frozendict>=2.0.0
Dynamic: license-file
